mspy_doc_builder/__init__.py
mspy_doc_builder/application.py
mspy_doc_builder/build.py
mspy_doc_builder-0.1.0.dist-info/entry_points.txt
mspy_doc_builder-0.1.0.dist-info/METADATA
mspy_doc_builder-0.1.0.dist-info/WHEEL
mspy_doc_builder-0.1.0.dist-info/RECORD
