Metadata-Version: 2.1
Name: mspy-doc-builder
Version: 0.1.0
Summary: misspy document builder.
Author: sonyakun
Requires-Python: >=3.11,<4.0
Classifier: Programming Language :: Python :: 3
Classifier: Programming Language :: Python :: 3.11
Requires-Dist: cleo (>=2.0.1,<3.0.0)
